labels/__init__.py
labels/py.typed
labels/advisories/__init__.py
labels/advisories/database.py
labels/advisories/images.py
labels/advisories/match_fixes.py
labels/advisories/roots.py
labels/advisories/utils.py
labels/config/__init__.py
labels/config/cache.py
labels/config/context.py
labels/config/utils.py
labels/core/__init__.py
labels/core/cli.py
labels/core/configurator.py
labels/core/merge_packages.py
labels/core/scanner.py
labels/core/source_dispatcher.py
labels/core/top_parents.py
labels/domain/__init__.py
labels/domain/cloudwatch.py
labels/domain/tracks.py
labels/enrichers/__init__.py
labels/enrichers/api_interface.py
labels/enrichers/dispatcher.py
labels/enrichers/utils.py
labels/enrichers/alpine/__init__.py
labels/enrichers/alpine/complete.py
labels/enrichers/alpine/get.py
labels/enrichers/dart/__init__.py
labels/enrichers/dart/complete.py
labels/enrichers/dart/get.py
labels/enrichers/debian/__init__.py
labels/enrichers/debian/complete.py
labels/enrichers/debian/get.py
labels/enrichers/dotnet/__init__.py
labels/enrichers/dotnet/complete.py
labels/enrichers/dotnet/get.py
labels/enrichers/golang/__init__.py
labels/enrichers/golang/complete.py
labels/enrichers/golang/get.py
labels/enrichers/java/__init__.py
labels/enrichers/java/complete.py
labels/enrichers/java/get.py
labels/enrichers/javascript/__init__.py
labels/enrichers/javascript/complete.py
labels/enrichers/javascript/get.py
labels/enrichers/php/__init__.py
labels/enrichers/php/complete.py
labels/enrichers/php/get.py
labels/enrichers/python/__init__.py
labels/enrichers/python/complete.py
labels/enrichers/python/get.py
labels/enrichers/ruby/__init__.py
labels/enrichers/ruby/complete.py
labels/enrichers/ruby/get.py
labels/integrations/__init__.py
labels/integrations/docker.py
labels/integrations/ecr.py
labels/model/__init__.py
labels/model/advisories.py
labels/model/constraints.py
labels/model/core.py
labels/model/file.py
labels/model/indexables.py
labels/model/metadata.py
labels/model/package.py
fluid_labels-3.1.5.dist-info/METADATA
fluid_labels-3.1.5.dist-info/WHEEL
fluid_labels-3.1.5.dist-info/entry_points.txt
fluid_labels-3.1.5.dist-info/RECORD
