Metadata-Version: 2.4
Name: fluid-labels
Version: 3.1.5
Summary: Fluid Attacks SBOM Library
Author-email: Fluid Attacks Development Team <development@fluidattacks.com>
Requires-Python: <4.0,>=3.11
Requires-Dist: aioboto3==15.0.0
Requires-Dist: beautifulsoup4==4.13.4
Requires-Dist: boto3==1.38.27
Requires-Dist: botocore==1.38.27
Requires-Dist: click==8.2.1
Requires-Dist: confuse==2.0.1
Requires-Dist: cvss==3.6
Requires-Dist: cyclonedx-python-lib[json-validation,validation,xml-validation]==11.0.0
Requires-Dist: defusedxml==0.7.1
Requires-Dist: diskcache==5.6.3
Requires-Dist: fluidattacks-core[logging,sarif,semver]<6.0.0,>=5.1.0
Requires-Dist: fluidattacks-tracks==0.6.0
Requires-Dist: gemfileparser==0.8.0
Requires-Dist: jsonschema==4.25.0
Requires-Dist: more-itertools==10.7.0
Requires-Dist: networkx==3.6.1
Requires-Dist: os-release==1.0.1
Requires-Dist: packageurl-python==0.17.1
Requires-Dist: packaging==25.0
Requires-Dist: pefile==2023.2.7
Requires-Dist: phpserialize==1.3
Requires-Dist: platformdirs==4.3.6
Requires-Dist: pydantic==2.12.3
Requires-Dist: reactivex==4.0.4
Requires-Dist: redis==6.2.0
Requires-Dist: requests==2.32.4
Requires-Dist: requirements-parser==0.11.0
Requires-Dist: spdx-tools==0.8.3
Requires-Dist: tree-sitter-json==0.24.8
Requires-Dist: tree-sitter-python==0.23.6
Requires-Dist: tree-sitter-swift==0.0.1
Requires-Dist: tree-sitter-toml==0.7.0
Requires-Dist: tree-sitter-yaml==0.7.0
Requires-Dist: tree-sitter==0.25.2
Requires-Dist: urllib3==2.6.3
Requires-Dist: zstd==1.5.6.7
